{"schema_version":1,"event_id":"create-587e36ce-d13c-4eff-8b5f-b552bee5d662","issue_id":"tau-sm7z","recorded_at":"2026-04-21T11:47:18.714Z","actor":"backlog","kind":"issue.created","fields":{"id":"tau-sm7z","title":"Audit follow-up: remove remaining sync persistence/execution-state getters","description":"Audit item C5 remains partial. execution-state and persistence still expose sync getSnapshot-style host bridges, and agent worker still publishes status with Effect.runSync at the host boundary. Move remaining runtime reads to effectful accessors or isolate the sync bridge behind a single host adapter, then rerun extensions/tau gate.","status":"open","priority":2,"issue_type":"task","created_at":"2026-04-21T11:47:18.714Z","created_by":"backlog","updated_at":"2026-04-21T11:47:18.714Z"}}
