{"schema_version":1,"event_id":"import-tau-neg.8","issue_id":"tau-neg.8","recorded_at":"2026-01-18T01:21:23.029Z","actor":"beads-import","kind":"issue.imported","source":{"system":"beads","issue_id":"tau-neg.8"},"fields":{"id":"tau-neg.8","title":"Add vitest coverage for sandbox policies (unit + gated integration)","description":"Add vitest coverage in tau extension workspace: policy merging, settings precedence, workspace root detection, realpath enforcement, approval decision logic. Add OS-gated integration tests for ASRT when env PI_SANDBOX_TESTS=1. DoD: green tests.","status":"closed","priority":1,"issue_type":"task","created_at":"2026-01-17T17:07:38.859097387+01:00","updated_at":"2026-01-18T02:21:23.029665597+01:00","closed_at":"2026-01-18T02:21:23.029665597+01:00","close_reason":"Added vitest coverage: approval.test.ts (38 tests for policy decision logic) + sandbox-bash.integration.test.ts (16 ASRT integration tests gated behind PI_SANDBOX_TESTS=1). Total: 83 tests (67 unit + 16 integration).","dependencies":[{"issue_id":"tau-neg.8","depends_on_id":"tau-neg","type":"parent-child","created_at":"2026-01-17T17:07:38.85938536+01:00","created_by":"daemon"},{"issue_id":"tau-neg.8","depends_on_id":"tau-neg.5","type":"blocks","created_at":"2026-01-17T17:08:33.871245832+01:00","created_by":"daemon"},{"issue_id":"tau-neg.8","depends_on_id":"tau-neg.4","type":"blocks","created_at":"2026-01-17T17:08:33.886092592+01:00","created_by":"daemon"},{"issue_id":"tau-neg.8","depends_on_id":"tau-neg.6","type":"blocks","created_at":"2026-01-17T17:08:33.901229175+01:00","created_by":"daemon"}]}}
