{"schema_version":1,"event_id":"import-tau-i3c.13","issue_id":"tau-i3c.13","recorded_at":"2026-01-18T13:29:41.266Z","actor":"beads-import","kind":"issue.imported","source":{"system":"beads","issue_id":"tau-i3c.13"},"fields":{"id":"tau-i3c.13","title":"Delete old extensions and update install script","description":"Clean up old extension folders and update deployment.\n\n## Delete\n- extensions/beads/\n- extensions/editor-hub/\n- extensions/exa/\n- extensions/sandbox/\n- extensions/skill-marker/\n- extensions/task/\n\n## Keep (but now has new structure)\n- extensions/tau/\n\n## Update scripts/pi/install-extensions.sh\n- Remove: beads, exa, task, editor-hub, sandbox, skill-marker from EXTS array\n- Keep only: tau\n\n## Update AGENTS.md\n- Remove references to separate extensions\n- Update any paths\n\n## DoD\n- Only extensions/tau/ exists\n- install-extensions.sh only installs tau\n- No broken symlinks in ~/.pi/agent/extensions/","status":"closed","priority":1,"issue_type":"task","created_at":"2026-01-17T19:49:35.045442391+01:00","updated_at":"2026-01-18T14:29:41.26677004+01:00","closed_at":"2026-01-18T14:29:41.26677004+01:00","close_reason":"Removed legacy extensions/, updated installer to install only tau and clean up old symlinks; updated AGENTS.md packaging notes","dependencies":[{"issue_id":"tau-i3c.13","depends_on_id":"tau-i3c","type":"parent-child","created_at":"2026-01-17T19:49:35.04585025+01:00","created_by":"ribelo"},{"issue_id":"tau-i3c.13","depends_on_id":"tau-i3c.12","type":"blocks","created_at":"2026-01-17T19:52:25.221002106+01:00","created_by":"ribelo"},{"issue_id":"tau-i3c.13","depends_on_id":"tau-i3c.1","type":"blocks","created_at":"2026-01-18T13:26:41.768942095+01:00","created_by":"ribelo"}]}}
