{"schema_version":1,"event_id":"update-ada77bb2-b19a-443e-8d40-0f29632b0609","issue_id":"tau-ch9q","recorded_at":"2026-04-28T00:36:12.397Z","actor":"backlog","kind":"issue.updated","set_fields":{"status":"closed","updated_at":"2026-04-28T00:36:12.397Z","closed_at":"2026-04-28T00:36:12.397Z","close_reason":"Fixed Ralph release capability restoration. Ralph now snapshots pre-contract active tools per session file, restores them when a controller/child session is released, refreshes Ralph ownership cache from canonical loop state, clears only released session cache entries, and normalizes cache keys to workspace root. Added regression tests for direct finish, waiting-loop finish, stale agent cache, targeted cache clearing, and root/subdir cache normalization. Verified with npm run gate in extensions/tau."},"unset_fields":[]}
