{"schema_version":1,"event_id":"update-f56bc16e-b9ab-491a-9cd4-4a75a85cc39a","issue_id":"tau-1pyv","recorded_at":"2026-04-22T00:43:10.780Z","actor":"backlog","kind":"issue.updated","set_fields":{"comments":[{"id":1,"issue_id":"tau-1pyv","author":"backlog","text":"Verified in current checkout with important nuance. extensions/tau/src/agents-menu/state.ts:303-311 enforces disabled-agent policy only from in-memory AgentSelectionStore state plus ralphOwnedSessionCache. isDisabledForCwd(...) returns existing?.disabledAgents.has(name) ?? false, so before activate(...) it defaults to enabled. isRalphOwnedSession(...) returns ralphOwnedSessionCache.get(cacheKey) ?? false, so Ralph policy only applies after preloadRalphOwnedSessionCache(...). AgentControl.spawn() uses isAgentDisabledForSession(...) synchronously for enforcement at extensions/tau/src/agent/control.ts:57-63. Headless session_start/session_switch paths call agentSelections.activate(...) but do not preload Ralph ownership (extensions/tau/src/agents-menu/index.ts:365-379,381-389), so Ralph-only restrictions can be bypassed there. More generally, if loadRegistrySafe(...) returns null during session startup, activate(...) is skipped while AgentControl.spawn() still performs its own AgentRegistry.load(...), leaving user disabled-agent enforcement dependent on prior cache warmup. Verified issue is that enforcement is cache-backed rather than authoritative; exact exploitability varies by path.","created_at":"2026-04-22T00:37:48.129Z"},{"id":2,"issue_id":"tau-1pyv","author":"backlog","text":"Implemented authoritative disable enforcement path used by AgentControl.spawn. Added AgentSelectionStore.resolveEnabledAgentsForSession(cwd, sessionFile, availableAgents) to refresh project settings + preload Ralph ownership on demand. Exposed this through agents-menu/index.ts as resolveEnabledAgentsForSessionAuthoritative. AgentControl.spawn now computes enabled agents through that authoritative path before enforcing disabled-agent errors, so enforcement no longer depends on prior UI/session cache warmup. Added regression test in extensions/tau/test/agents-settings.test.ts: resolves authoritative session restrictions without prior activate/preload.","created_at":"2026-04-22T00:43:10.780Z"}],"updated_at":"2026-04-22T00:43:10.780Z"},"unset_fields":[]}
